awslabs/__init__.py
awslabs/aws_api_mcp_server/__init__.py
awslabs/aws_api_mcp_server/server.py
awslabs/aws_api_mcp_server/core/__init__.py
awslabs/aws_api_mcp_server/core/py.typed
awslabs/aws_api_mcp_server/core/agent_scripts/__init__.py
awslabs/aws_api_mcp_server/core/agent_scripts/manager.py
awslabs/aws_api_mcp_server/core/agent_scripts/models.py
awslabs/aws_api_mcp_server/core/agent_scripts/registry/__init__.py
awslabs/aws_api_mcp_server/core/agent_scripts/registry/application-failure-troubleshooting.script.md
awslabs/aws_api_mcp_server/core/agent_scripts/registry/cloudtral-mutli-region-setup.script.md
awslabs/aws_api_mcp_server/core/agent_scripts/registry/create_amazon_aurora_db_cluster_with_instances.script.md
awslabs/aws_api_mcp_server/core/agent_scripts/registry/lambda-timeout-debugging.script.md
awslabs/aws_api_mcp_server/core/agent_scripts/registry/scripts_format.md
awslabs/aws_api_mcp_server/core/agent_scripts/registry/troubleshoot-permissions-with-cloudtrail-events.script.md
awslabs/aws_api_mcp_server/core/aws/__init__.py
awslabs/aws_api_mcp_server/core/aws/driver.py
awslabs/aws_api_mcp_server/core/aws/pagination.py
awslabs/aws_api_mcp_server/core/aws/regions.py
awslabs/aws_api_mcp_server/core/aws/service.py
awslabs/aws_api_mcp_server/core/aws/services.py
awslabs/aws_api_mcp_server/core/common/__init__.py
awslabs/aws_api_mcp_server/core/common/command.py
awslabs/aws_api_mcp_server/core/common/command_metadata.py
awslabs/aws_api_mcp_server/core/common/config.py
awslabs/aws_api_mcp_server/core/common/errors.py
awslabs/aws_api_mcp_server/core/common/file_system_controls.py
awslabs/aws_api_mcp_server/core/common/help_command.py
awslabs/aws_api_mcp_server/core/common/helpers.py
awslabs/aws_api_mcp_server/core/common/models.py
awslabs/aws_api_mcp_server/core/common/py.typed
awslabs/aws_api_mcp_server/core/data/api_metadata.json
awslabs/aws_api_mcp_server/core/metadata/__init__.py
awslabs/aws_api_mcp_server/core/metadata/read_only_operations_list.py
awslabs_aws_api_mcp_server-1.3.4.dist-info/METADATA
awslabs_aws_api_mcp_server-1.3.4.dist-info/WHEEL
awslabs_aws_api_mcp_server-1.3.4.dist-info/entry_points.txt
awslabs_aws_api_mcp_server-1.3.4.dist-info/licenses/LICENSE
awslabs_aws_api_mcp_server-1.3.4.dist-info/licenses/NOTICE
awslabs_aws_api_mcp_server-1.3.4.dist-info/RECORD
