Metadata-Version: 2.4
Name: awslabs.aws-api-mcp-server
Version: 1.3.4
Summary: Model Context Protocol (MCP) server for interacting with AWS
Project-URL: homepage, https://awslabs.github.io/mcp/
Project-URL: docs, https://awslabs.github.io/mcp/servers/aws-api-mcp-server/
Project-URL: documentation, https://awslabs.github.io/mcp/servers/aws-api-mcp-server/
Project-URL: repository, https://github.com/awslabs/mcp.git
Project-URL: changelog, https://github.com/awslabs/mcp/blob/main/src/aws-api-mcp-server/CHANGELOG.md
Author: Amazon Web Services
Author-email: AWSLabs MCP <203918161+awslabs-mcp@users.noreply.github.com>
License: Apache-2.0
License-File: LICENSE
License-File: NOTICE
Classifier: License :: OSI Approved :: Apache Software License
Classifier: Operating System :: OS Independent
Classifier: Programming Language :: Python
Classifier: Programming Language :: Python :: 3
Classifier: Programming Language :: Python :: 3.10
Classifier: Programming Language :: Python :: 3.11
Classifier: Programming Language :: Python :: 3.12
Classifier: Programming Language :: Python :: 3.13
Requires-Python: >=3.10
Requires-Dist: awscli==1.44.17
Requires-Dist: boto3>=1.41.0
Requires-Dist: botocore[crt]>=1.41.0
Requires-Dist: fastmcp>=2.14.0
Requires-Dist: importlib-resources>=6.0.0
Requires-Dist: loguru>=0.7.3
Requires-Dist: lxml>=5.1.0
Requires-Dist: mcp>=1.23.0
Requires-Dist: pydantic>=2.10.6
Requires-Dist: python-frontmatter>=1.1.0
Requires-Dist: python-json-logger>=2.0.7
Requires-Dist: requests>=2.32.4
Requires-Dist: setuptools>=69.0.0
